cvefinder/__init__.py
cvefinder/__main__.py
cvefinder/cve_scraper.py
cver/__init__.py
cver/__main__.py
cver/cve_scraper.py
cvefinder-1.0.2.dist-info/LICENSE
cvefinder-1.0.2.dist-info/METADATA
cvefinder-1.0.2.dist-info/WHEEL
cvefinder-1.0.2.dist-info/dependency_links.txt
cvefinder-1.0.2.dist-info/entry_points.txt
cvefinder-1.0.2.dist-info/top_level.txt
cvefinder-1.0.2.dist-info/RECORD
