Metadata-Version: 2.1
Name: cvefinder
Version: 1.0.2
Summary: A simple commandline app for searching and looking up opensource vulnerabilities
Home-page: UNKNOWN
Author: Vipin Kumar
Author-email: vpnkumar.kumar1@gmail.com
License: MIT
Platform: UNKNOWN
Classifier: License :: OSI Approved :: MIT License
Classifier: Programming Language :: Python :: 3
Classifier: Programming Language :: Python :: 3.7
Requires-Python: >=3.0
Requires-Dist: beautifulsoup4 (==4.9.3)
Requires-Dist: bleach (==4.0.0)
Requires-Dist: certifi (==2021.5.30)
Requires-Dist: charset-normalizer (==2.0.4)
Requires-Dist: click (==8.0.1)
Requires-Dist: colorama (==0.4.4)
Requires-Dist: docutils (==0.17.1)
Requires-Dist: idna (==3.2)
Requires-Dist: importlib-metadata (==4.6.4)
Requires-Dist: keyring (==23.0.1)
Requires-Dist: lxml (==4.6.3)
Requires-Dist: packaging (==21.0)
Requires-Dist: pkginfo (==1.7.1)
Requires-Dist: Pygments (==2.10.0)
Requires-Dist: pyparsing (==2.4.7)
Requires-Dist: readme-renderer (==29.0)
Requires-Dist: requests (==2.26.0)
Requires-Dist: requests-toolbelt (==0.9.1)
Requires-Dist: rfc3986 (==1.5.0)
Requires-Dist: six (==1.16.0)
Requires-Dist: soupsieve (==2.2.1)
Requires-Dist: tqdm (==4.62.1)
Requires-Dist: twine (==3.4.2)
Requires-Dist: typing-extensions (==3.10.0.0)
Requires-Dist: urllib3 (==1.26.6)
Requires-Dist: webencodings (==0.5.1)
Requires-Dist: zipp (==3.5.0)
